vue_ssr/__init__.py
vue_ssr/apps.py
vue_ssr/services.py
vue_ssr/settings.py
vue_ssr/vue_ssr.py
vue_ssr/templatetags/__init__.py
vue_ssr/templatetags/vue_ssr.py
vue_ssr-0.1.0.dist-info/licenses/LICENSE
vue_ssr-0.1.0.dist-info/METADATA
vue_ssr-0.1.0.dist-info/WHEEL
vue_ssr-0.1.0.dist-info/top_level.txt
vue_ssr-0.1.0.dist-info/RECORD
