Metadata-Version: 2.4
Name: vue-ssr
Version: 0.1.0
Summary: Render Vue components on the server side
Requires-Python: >=3.11
License-File: LICENSE
Requires-Dist: requests>=2.0.0
Requires-Dist: requests-unixsocket>=0.4.1
Dynamic: license-file
